micropython_wsentids/__init__.py
micropython_wsentids/i2c_helpers.py
micropython_wsentids/wsentids.py
micropython_wsentids-0.1.0.dist-info/LICENSE
micropython_wsentids-0.1.0.dist-info/METADATA
micropython_wsentids-0.1.0.dist-info/WHEEL
micropython_wsentids-0.1.0.dist-info/top_level.txt
micropython_wsentids-0.1.0.dist-info/RECORD
