Metadata-Version: 2.1
Name: micropython-wsentids
Version: 0.1.0
Summary: MicroPython library for the WSEN WSEN-TIDS temperautre Sensor
Author-email: JDM <xxyx@mailmeto.mozmail.com>
License: MIT
Project-URL: Homepage, https://github.com/jposada202020/MicroPython_WSENTIDS
Keywords: sensor,micropython,wsentids,wsen,micropython,temperature,driver,sensor,tids
Classifier: Intended Audience :: Developers
Classifier: Topic :: Software Development :: Libraries
Classifier: Topic :: Software Development :: Embedded Systems
Classifier: Topic :: System :: Hardware
Classifier: License :: OSI Approved :: MIT License
Classifier: Programming Language :: Python :: Implementation :: MicroPython
License-File: LICENSE
